README.md
setup.cfg
setup.py
gopygo/__init__.py
gopygo/ast.py
gopygo/enums.py
gopygo/exceptions.py
gopygo/parser.py
gopygo/unparser.py
gopygo.egg-info/PKG-INFO
gopygo.egg-info/SOURCES.txt
gopygo.egg-info/dependency_links.txt
gopygo.egg-info/not-zip-safe
gopygo.egg-info/requires.txt
gopygo.egg-info/top_level.txt