Metadata-Version: 2.1
Name: gopygo
Version: 0.3.0
Summary: Pure Python Go parser, AST and unparser library
Home-page: http://github.com/up9inc/gopygo
Author: M. Mert Yildiran
Author-email: mehmet@up9.com
License: UNKNOWN
Platform: UNKNOWN
Classifier: Programming Language :: Python
Classifier: Development Status :: 4 - Beta
Classifier: Operating System :: OS Independent
Classifier: License :: OSI Approved :: MIT License
Classifier: Intended Audience :: Developers
Classifier: Topic :: Software Development :: Libraries
Provides-Extra: dev
